pteropy/__init__.py
pteropy/pteropy.py
pteropy-0.1.9.dist-info/LICENSE
pteropy-0.1.9.dist-info/METADATA
pteropy-0.1.9.dist-info/WHEEL
pteropy-0.1.9.dist-info/top_level.txt
pteropy-0.1.9.dist-info/RECORD
