Metadata-Version: 2.1
Name: pteropy
Version: 0.1.9
Summary: 簡單存取Pterodactyl api
Home-page: https://github.com/HansHans135/pteropy
Author: Hans
Author-email: ccoccc14@gmail.com
License: UNKNOWN
Platform: UNKNOWN
Classifier: Development Status :: 1 - Planning
Classifier: License :: OSI Approved :: MIT License
Classifier: Operating System :: OS Independent
Requires-Python: >=3.6
License-File: LICENSE
